{"DOMDocument":{"Shape":[{"charid":"1","path":[{"color":"#00b7c6","colorOpacity":"1","d":"M 272 131.85l3.5 -3.85l-6.95 0l3.45 3.85","pathType":"Fill","stroke":"none"}]},{"charid":"2","path":[{"color":"#00b7c6","colorOpacity":"1","d":"M 275.5 125.05l-3.5 -3.9l-3.45 3.9l6.95 0","pathType":"Fill","stroke":"none"}]},{"charid":"3","path":[{"color":"#00b7c6","colorOpacity":"1","d":"M 277.25 117.45q0 -0.9 -0.6 -1.55q-0.65 -0.65 -1.55 -0.65q-0.95 0 -1.55 0.65q-0.65 0.65 -0.65 1.55q0 0.95 0.65 1.55q0.6 0.65 1.55 0.65q0.9 0 1.55 -0.65q0.6 -0.6 0.6 -1.55","pathType":"Fill","stroke":"none"}]},{"charid":"13","path":[{"color":"#f8fbfd","colorOpacity":"1","d":"M 279 88.25l-13.75 0l0 46.05l13.75 0l0 -46.05","pathType":"Fill","stroke":"none"}]},{"charid":"14","path":[{"color":"#006983","colorOpacity":"1","d":"M 136.45 12.35l0 -10l-13.4 0l0 10l13.4 0","pathType":"Fill","stroke":"none"}]},{"charid":"15","path":[{"color":"#006983","colorOpacity":"1","d":"M 118.8 7.35q0 -2.3 -1.6 -3.9q-1.6 -1.6 -3.9 -1.6q-2.3 0 -3.9 1.6q-1.6 1.6 -1.6 3.9q0 2.3 1.6 3.9q1.6 1.6 3.9 1.6q2.3 0 3.9 -1.6q1.6 -1.6 1.6 -3.9","pathType":"Fill","stroke":"none"}]},{"charid":"17","path":[{"color":"#dee0e2","colorOpacity":"1","d":"M 250.65 14.7l4.4 -7.35l-250.6 0l4.4 7.35l241.8 0","pathType":"Fill","stroke":"none"}]},{"charid":"18","path":[{"color":"#f8fbfd","colorOpacity":"1","d":"M 0 321.15l8.85 0l0 -306.45l241.8 0l0 306.45l8.8 0l0 -321.15l-259.45 0l0 321.15","pathType":"Fill","stroke":"none"}]},{"charid":"19","path":[{"color":"#c6c4c4","colorOpacity":"1","d":"M 250.65 19.1l0 -4.4l-241.8 0l0 4.4l241.8 0","pathType":"Fill","stroke":"none"}]},{"charid":"20","path":[{"color":"#d1d1d1","colorOpacity":"1","d":"M 17.25 14.7l-8.4 0l0 306.45l8.4 0l0 -306.45","pathType":"Fill","stroke":"none"}]},{"charid":"43","path":[{"color":"#ffffff","colorOpacity":"1","d":"M 12.9 14.05l0 308.95l236.6 0l0 -308.95l-236.6 0","pathType":"Fill","stroke":"none"},{"color":"#ffffff","colorOpacity":"1","d":"M 12.9 14.05l236.6 0l0 308.95l-236.6 0l0 -308.95","strokeWidth":"4","fill":"none","strokeLinecap":"round","strokeLinejoin":"round","pathType":"Stroke"}]},{"charid":"44","path":[{"color":"#afc52a","colorOpacity":"1","d":"M 118.3 0l-118.3 0l0 308.95l118.3 0l0 -308.95","pathType":"Fill","stroke":"none"},{"color":"#006983","colorOpacity":"1","d":"M 0 0l118.3 0l0 308.95l-118.3 0l0 -308.95","strokeWidth":"1","fill":"none","strokeLinecap":"round","strokeLinejoin":"round","pathType":"Stroke"}]},{"charid":"46","path":[{"color":"#24333a","colorOpacity":"1","d":"M 40.7 31.7q0.95 0 1.8 -0.6l-0.5 -0.55q-1.1 0.9 -2.4 0.15l-0.35 0.6q0.65 0.4 1.45 0.4","pathType":"Fill","stroke":"none"}]},{"charid":"47","path":[{"color":"#24333a","colorOpacity":"1","d":"M 44.3 35.55l-0.2 -0.7q-3.75 1.3 -7.1 0l-0.3 0.65q1.25 0.5 2.75 0.65q2.45 0.25 4.85 -0.6","pathType":"Fill","stroke":"none"}]},{"charid":"48","path":[{"color":"#24333a","colorOpacity":"1","d":"M 33.5 20.2l0.35 -0.25q2.6 -1.55 4.05 -1l0.05 -0.05q-1.55 -0.6 -4.1 1l-0.4 0.2l0.05 0.1","pathType":"Fill","stroke":"none"}]},{"charid":"49","path":[{"color":"#24333a","colorOpacity":"1","d":"M 46.7 23.8q0 -0.7 -0.5 -1.15q-0.5 -0.5 -1.2 -0.5q-0.65 0 -1.15 0.5q-0.5 0.5 -0.5 1.15q0 0.7 0.5 1.2q0.45 0.5 1.15 0.5q0.7 0 1.2 -0.5q0.5 -0.5 0.5 -1.2","pathType":"Fill","stroke":"none"}]},{"charid":"51","path":[{"color":"#f6b251","colorOpacity":"1","d":"M 92 55.6q0.2 -1.05 -0.65 -1.85l-0.9 -0.65l-7.85 0q-3.6 0 -4.25 2.55q-0.35 1.25 0.05 2.5q0.75 8.2 3.85 11.15q1.5 1.5 2.9 1.3q8.05 -1.45 5.7 -7.5q-0.75 -1.9 -2.4 -4.05l-1.55 -1.75l2.75 0l1.05 -0.2q1.1 -0.45 1.3 -1.5","pathType":"Fill","stroke":"none"}]},{"charid":"52","path":[{"color":"#6e868e","colorOpacity":"1","d":"M 33.2 45.3q-1.2 0.1 -3.7 0.5l-7.75 24.75l5.8 1.65l-4.95 3.15l5.3 20.5l5.3 -50.55","pathType":"Fill","stroke":"none"}]},{"charid":"53","path":[{"color":"#3c535f","colorOpacity":"1","d":"M 68.65 55l-3.25 32.95l7.55 19.75l4.05 0l8.35 -37.15l-6.95 -12.4l-4.85 19.6l-4.9 -22.75","pathType":"Fill","stroke":"none"}]},{"charid":"54","path":[{"color":"#3c535f","colorOpacity":"1","d":"M 33.2 45.3q-6 0.45 -14.2 3.7q-4.15 1.6 -7.05 3.15l0 94.45l10.65 0l10.6 -101.3","pathType":"Fill","stroke":"none"}]},{"charid":"55","path":[{"color":"#6e868e","colorOpacity":"1","d":"M 52 46.05q-3 -0.7 -4.05 -0.9q1.1 24.55 3.95 50.8l6.4 -16.4l-4.25 -5.05l5.3 -1.9l-7.35 -26.55","pathType":"Fill","stroke":"none"}]},{"charid":"56","path":[{"color":"#3c535f","colorOpacity":"1","d":"M 68.65 55q-0.95 -1.6 -4.05 -3.65q-6.15 -4.1 -16.65 -6.2q0.8 18.15 2.85 39.85q4.1 43.5 10.25 61.6l7.5 0l0.1 -91.6","pathType":"Fill","stroke":"none"}]},{"charid":"57","path":[{"color":"#f6b251","colorOpacity":"1","d":"M 47.05 47.6l0 -11.8l-13.85 0l0 11.8q-2.6 0.8 -4.1 2.05q-1.55 1.3 -1.55 2.75q0 2.35 3.7 4.05q3.7 1.7 8.9 1.7q5.2 0 8.9 -1.7q3.7 -1.7 3.7 -4.05q0 -1.45 -1.55 -2.75q-1.5 -1.25 -4.15 -2.05","pathType":"Fill","stroke":"none"}]},{"charid":"58","path":[{"color":"#e0685f","colorOpacity":"1","d":"M 40.15 46.95q-4.2 0.15 -9.65 1.2q-10.85 2.2 -17.15 7.05l1.4 72.2l49.3 0l1.35 -73.8q-2.55 -1.65 -7 -3.35q-8.85 -3.35 -18.25 -3.3","pathType":"Fill","stroke":"none"}]},{"charid":"59","path":[{"color":"#9b4545","colorOpacity":"1","d":"M 5.35 156.95q-0.4 0.4 -0.4 0.9l0 7.75q0 0.5 0.4 0.9q0.35 0.35 0.9 0.35q0.55 0 0.9 -0.35q0.35 -0.35 0.35 -0.9l0 -7.75q0 -0.5 -0.35 -0.9q-0.35 -0.35 -0.9 -0.35q-0.55 0 -0.9 0.35","pathType":"Fill","stroke":"none"}]},{"charid":"60","path":[{"color":"#9b4545","colorOpacity":"1","d":"M 10.9 165.6l-9.35 0l0 53.95l9.35 0l0 -53.95","pathType":"Fill","stroke":"none"}]},{"charid":"61","path":[{"color":"#f6b251","colorOpacity":"1","d":"M 10.25 151.65l-8.05 0l-0.25 1.1q-0.25 1.75 -0.35 5.2q-0.25 6.3 7.55 3.95q1.95 -0.6 1.75 -3.6l-0.65 -2.85l0 -3.8","pathType":"Fill","stroke":"none"}]},{"charid":"62","path":[{"color":"#3c535f","colorOpacity":"1","d":"M 14.75 76l-2.8 -23.85l-1.3 0.8q-1.55 1.15 -2.95 3q-4.4 5.8 -5.2 16.05l-2.5 79.65l11.95 0l2.8 -75.65","pathType":"Fill","stroke":"none"}]},{"charid":"63","path":[{"color":"#000000","colorOpacity":"1","d":"M 38.45 138.65l1.9 0l6.25 94.9l11.4 0l6.05 -106.15l-49.3 0l6.05 106.15l11.35 0l6.3 -94.9","pathType":"Fill","stroke":"none"},{"color":"#000000","colorOpacity":"1","d":"M 64.05 127.4l-6.05 106.15l-11.4 0l-6.25 -94.9l-1.9 0l-6.3 94.9l-11.35 0l-6.05 -106.15l49.3 0","strokeWidth":"0.5","fill":"none","strokeLinecap":"butt","strokeLinejoin":"miter","stroke-miterlimit":"10","pathType":"Stroke"}]},{"charid":"64","path":[{"color":"#9b4545","colorOpacity":"1","d":"M 32.2 233.55l-11.4 0l-1.7 4.9l-12 3.9l0 4.5l25.1 0l0 -13.3","pathType":"Fill","stroke":"none"}]},{"charid":"65","path":[{"color":"#9b4545","colorOpacity":"1","d":"M 58 233.55l-11.4 0l0 13.3l25.1 0l0 -4.5l-12 -3.9l-1.7 -4.9","pathType":"Fill","stroke":"none"}]},{"charid":"66","path":[{"color":"#24333a","colorOpacity":"1","d":"M 51.2 6.25q-4.15 -5.95 -9.3 -6.25q-4.65 -0.25 -8.4 3.95q-3.6 0.15 -6 2.75q-4.85 5.3 1.15 17.85q0.2 -3.85 1.45 -7.55q2.5 -7.45 7.7 -6.85l2.65 1.45q3.2 1.65 6.25 2.7q9.65 3.25 13.6 -1.2q-1.05 0 -2.75 -0.85q-3.35 -1.75 -6.35 -6","pathType":"Fill","stroke":"none"}]},{"charid":"67","path":[{"color":"#f6b251","colorOpacity":"1","d":"M 40.95 42.1q5.7 0.4 8.3 -3.25q1.3 -1.8 1.45 -3.7l0 -3.35q1.4 0 2.35 -1.05q1 -1.05 1 -2.55q0 -1.5 -1 -2.55q-0.95 -1.1 -2.35 -1.1l0 -12.4q-3.55 -7.3 -13.15 -4.35q-3 0.9 -6.25 2.7l-2.65 1.65l0 12.45l-0.5 -0.05q-1.4 0 -2.4 1.1q-1 1.05 -1 2.55q0 1.5 1 2.55q1 1.05 2.4 1.05l0.5 -0.05l0 3.4q1.2 4.35 6.85 6.1q2.85 0.85 5.45 0.85","pathType":"Fill","stroke":"none"}]},{"charid":"68","path":[{"color":"#c6c6c2","colorOpacity":"1","d":"M 241.8 80.85l0 -80.85l-241.8 0l0 80.85l118 -79.7l123.8 79.7","pathType":"Fill","stroke":"none"}]},{"charid":"69","path":[{"color":"#cecec8","colorOpacity":"1","d":"M 241.8 306.45l0 -306.45l-241.8 0l0 306.45l241.8 0","pathType":"Fill","stroke":"none"}]},{"charid":"72","path":[{"color":"#24333a","colorOpacity":"1","d":"M 33.5 20.2l0.35 -0.25q2.6 -1.55 4.05 -1l0.05 -0.05q-1.55 -0.6 -4.1 1l-0.4 0.2l0.05 0.1","pathType":"Fill","stroke":"none"}]}],"Bitmaps":[],"Sounds":[],"Text":[],"Timeline":[{"charid":"45","frameCount":"1","name":"Door","Frame":[{"num":"0","Command":[{"cmdType":"Place","charid":"44","objectId":"1","placeAfter":"0","transformMatrix":"1,0,0,1,0,0"}]}]},{"frameCount":"328","Frame":[{"num":"0","Command":[{"cmdType":"Place","charid":"1","objectId":"1","placeAfter":"0","transformMatrix":"1,0,0,1,2,3.85"},{"cmdType":"Place","charid":"2","objectId":"2","placeAfter":"1","transformMatrix":"1,0,0,1,2,3.85"},{"cmdType":"Place","charid":"3","objectId":"3","placeAfter":"2","transformMatrix":"1,0,0,1,2,3.85"},{"cmdType":"Place","charid":"3","objectId":"4","placeAfter":"3","transformMatrix":"1,0,0,1,-3.9,3.85"},{"cmdType":"Place","charid":"3","objectId":"5","placeAfter":"4","transformMatrix":"1,0,0,1,2,-2.15"},{"cmdType":"Place","charid":"3","objectId":"6","placeAfter":"5","transformMatrix":"1,0,0,1,-3.9,-2.15"},{"cmdType":"Place","charid":"3","objectId":"7","placeAfter":"6","transformMatrix":"1,0,0,1,2,-8.2"},{"cmdType":"Place","charid":"3","objectId":"8","placeAfter":"7","transformMatrix":"1,0,0,1,-3.9,-8.2"},{"cmdType":"Place","charid":"3","objectId":"9","placeAfter":"8","transformMatrix":"1,0,0,1,2,-14.25"},{"cmdType":"Place","charid":"3","objectId":"10","placeAfter":"9","transformMatrix":"1,0,0,1,-3.9,-14.25"},{"cmdType":"Place","charid":"3","objectId":"11","placeAfter":"10","transformMatrix":"1,0,0,1,2,-20.25"},{"cmdType":"Place","charid":"3","objectId":"12","placeAfter":"11","transformMatrix":"1,0,0,1,-3.9,-20.25"},{"cmdType":"Place","charid":"13","objectId":"13","placeAfter":"12","transformMatrix":"1,0,0,1,2,3.85"},{"cmdType":"Place","charid":"14","objectId":"14","placeAfter":"13","transformMatrix":"1,0,0,1,2,3.85"},{"cmdType":"Place","charid":"15","objectId":"15","placeAfter":"14","transformMatrix":"1,0,0,1,2,3.85"},{"cmdType":"Place","charid":"15","objectId":"16","placeAfter":"15","transformMatrix":"1,0,0,1,34.9,3.85"},{"cmdType":"Place","charid":"17","objectId":"17","placeAfter":"16","transformMatrix":"1,0,0,1,2,3.85"},{"cmdType":"Place","charid":"18","objectId":"18","placeAfter":"17","transformMatrix":"1,0,0,1,2,3.85"},{"cmdType":"Place","charid":"19","objectId":"19","placeAfter":"18","transformMatrix":"1,0,0,1,2,3.85"},{"cmdType":"Place","charid":"20","objectId":"20","placeAfter":"19","transformMatrix":"1,0,0,1,2,3.85"},{"cmdType":"Place","charid":"17","objectId":"21","placeAfter":"20","transformMatrix":"0.034,0,0,41.694,244.1,-287.9"},{"cmdType":"Place","charid":"43","objectId":"22","placeAfter":"21","transformMatrix":"1,0,0,1,0,0"},{"cmdType":"Place","charid":"45","objectId":"23","placeAfter":"22","transformMatrix":"1,0,0,1,131.2,14.05"},{"cmdType":"UpdateColorTransform","objectId":"23","colorMatrix":"1,0,1,0,1,0,1,0,"},{"cmdType":"UpdateVisibility","objectId":"23","visibility":"true"},{"cmdType":"UpdateBlendMode","objectId":"23","blendMode":"Normal"},{"cmdType":"Place","charid":"45","objectId":"24","placeAfter":"23","transformMatrix":"1,0,0,1,12.9,14.05"},{"cmdType":"UpdateColorTransform","objectId":"24","colorMatrix":"1,0,1,0,1,0,1,0,"},{"cmdType":"UpdateVisibility","objectId":"24","visibility":"true"},{"cmdType":"UpdateBlendMode","objectId":"24","blendMode":"Normal"},{"cmdType":"Place","charid":"46","objectId":"25","placeAfter":"24","transformMatrix":"1,0,0,1,153.5,76.8"},{"cmdType":"Place","charid":"47","objectId":"26","placeAfter":"25","transformMatrix":"1,0,0,1,153.5,76.8"},{"cmdType":"Place","charid":"48","objectId":"27","placeAfter":"26","transformMatrix":"1,0,0,1,153.5,76.8"},{"cmdType":"Place","charid":"49","objectId":"28","placeAfter":"27","transformMatrix":"1,0,0,1,153.5,76.8"},{"cmdType":"Place","charid":"49","objectId":"29","placeAfter":"28","transformMatrix":"1.015,0,0,1,143.7,76.85"},{"cmdType":"Place","charid":"51","objectId":"30","placeAfter":"29","transformMatrix":"1,0,0,1,153.5,76.8"},{"cmdType":"Place","charid":"52","objectId":"31","placeAfter":"30","transformMatrix":"1,0,0,1,153.5,76.8"},{"cmdType":"Place","charid":"53","objectId":"32","placeAfter":"31","transformMatrix":"1,0,0,1,153.5,76.8"},{"cmdType":"Place","charid":"54","objectId":"33","placeAfter":"32","transformMatrix":"1,0,0,1,153.5,76.8"},{"cmdType":"Place","charid":"55","objectId":"34","placeAfter":"33","transformMatrix":"1,0,0,1,153.5,76.8"},{"cmdType":"Place","charid":"56","objectId":"35","placeAfter":"34","transformMatrix":"1,0,0,1,153.5,76.8"},{"cmdType":"Place","charid":"57","objectId":"36","placeAfter":"35","transformMatrix":"1,0,0,1,153.5,76.8"},{"cmdType":"Place","charid":"58","objectId":"37","placeAfter":"36","transformMatrix":"1,0,0,1,153.5,76.8"},{"cmdType":"Place","charid":"59","objectId":"38","placeAfter":"37","transformMatrix":"1,0,0,1,153.5,76.8"},{"cmdType":"Place","charid":"60","objectId":"39","placeAfter":"38","transformMatrix":"1,0,0,1,153.5,76.8"},{"cmdType":"Place","charid":"61","objectId":"40","placeAfter":"39","transformMatrix":"1,0,0,1,153.5,76.8"},{"cmdType":"Place","charid":"62","objectId":"41","placeAfter":"40","transformMatrix":"1,0,0,1,153.5,76.8"},{"cmdType":"Place","charid":"63","objectId":"42","placeAfter":"41","transformMatrix":"1,0,0,1,153.5,76.8"},{"cmdType":"Place","charid":"64","objectId":"43","placeAfter":"42","transformMatrix":"1,0,0,1,153.5,76.8"},{"cmdType":"Place","charid":"65","objectId":"44","placeAfter":"43","transformMatrix":"1,0,0,1,153.5,76.8"},{"cmdType":"Place","charid":"66","objectId":"45","placeAfter":"44","transformMatrix":"1,0,0,1,153.5,76.8"},{"cmdType":"Place","charid":"67","objectId":"46","placeAfter":"45","transformMatrix":"1,0,0,1,153.5,76.8"},{"cmdType":"Place","charid":"68","objectId":"47","placeAfter":"46","transformMatrix":"1,0,0,1,12.6,17.2"},{"cmdType":"Place","charid":"69","objectId":"48","placeAfter":"47","transformMatrix":"1,0,0,1,12.6,17.2"},{"cmdType":"UpdateMask","objectId":"22","maskTill":"24"}]},{"num":"125","Command":[{"cmdType":"Move","objectId":"23","transformMatrix":"1,0,0,1,141.7,14.05"},{"cmdType":"Move","objectId":"24","transformMatrix":"1,0,0,1,2.7,14.05"}]},{"num":"126","Command":[{"cmdType":"Move","objectId":"23","transformMatrix":"1,0,0,1,151.75,14.05"},{"cmdType":"Move","objectId":"24","transformMatrix":"1,0,0,1,-7.05,14.05"}]},{"num":"127","Command":[{"cmdType":"Move","objectId":"23","transformMatrix":"1,0,0,1,161.25,14.05"},{"cmdType":"Move","objectId":"24","transformMatrix":"1,0,0,1,-16.3,14.05"}]},{"num":"128","Command":[{"cmdType":"Move","objectId":"23","transformMatrix":"1,0,0,1,170.3,14.05"},{"cmdType":"Move","objectId":"24","transformMatrix":"1,0,0,1,-25.1,14.05"}]},{"num":"129","Command":[{"cmdType":"Move","objectId":"23","transformMatrix":"1,0,0,1,178.85,14.05"},{"cmdType":"Move","objectId":"24","transformMatrix":"1,0,0,1,-33.4,14.05"}]},{"num":"130","Command":[{"cmdType":"Move","objectId":"23","transformMatrix":"1,0,0,1,186.95,14.05"},{"cmdType":"Move","objectId":"24","transformMatrix":"1,0,0,1,-41.25,14.05"}]},{"num":"131","Command":[{"cmdType":"Move","objectId":"23","transformMatrix":"1,0,0,1,194.5,14.05"},{"cmdType":"Move","objectId":"24","transformMatrix":"1,0,0,1,-48.6,14.05"}]},{"num":"132","Command":[{"cmdType":"Move","objectId":"23","transformMatrix":"1,0,0,1,201.6,14.05"},{"cmdType":"Move","objectId":"24","transformMatrix":"1,0,0,1,-55.45,14.05"}]},{"num":"133","Command":[{"cmdType":"Move","objectId":"23","transformMatrix":"1,0,0,1,208.2,14.05"},{"cmdType":"Move","objectId":"24","transformMatrix":"1,0,0,1,-61.9,14.05"}]},{"num":"134","Command":[{"cmdType":"Move","objectId":"23","transformMatrix":"1,0,0,1,214.3,14.05"},{"cmdType":"Move","objectId":"24","transformMatrix":"1,0,0,1,-67.8,14.05"}]},{"num":"135","Command":[{"cmdType":"Move","objectId":"23","transformMatrix":"1,0,0,1,219.95,14.05"},{"cmdType":"Move","objectId":"24","transformMatrix":"1,0,0,1,-73.25,14.05"}]},{"num":"136","Command":[{"cmdType":"Move","objectId":"23","transformMatrix":"1,0,0,1,225.05,14.05"},{"cmdType":"Move","objectId":"24","transformMatrix":"1,0,0,1,-78.25,14.05"}]},{"num":"137","Command":[{"cmdType":"Move","objectId":"23","transformMatrix":"1,0,0,1,229.7,14.05"},{"cmdType":"Move","objectId":"24","transformMatrix":"1,0,0,1,-82.75,14.05"}]},{"num":"138","Command":[{"cmdType":"Move","objectId":"23","transformMatrix":"1,0,0,1,233.85,14.05"},{"cmdType":"Move","objectId":"24","transformMatrix":"1,0,0,1,-86.8,14.05"}]},{"num":"139","Command":[{"cmdType":"Move","objectId":"23","transformMatrix":"1,0,0,1,237.5,14.05"},{"cmdType":"Move","objectId":"24","transformMatrix":"1,0,0,1,-90.35,14.05"}]},{"num":"140","Command":[{"cmdType":"Move","objectId":"23","transformMatrix":"1,0,0,1,240.7,14.05"},{"cmdType":"Move","objectId":"24","transformMatrix":"1,0,0,1,-93.45,14.05"}]},{"num":"141","Command":[{"cmdType":"Move","objectId":"23","transformMatrix":"1,0,0,1,243.4,14.05"},{"cmdType":"Move","objectId":"24","transformMatrix":"1,0,0,1,-96.05,14.05"}]},{"num":"142","Command":[{"cmdType":"Move","objectId":"23","transformMatrix":"1,0,0,1,245.6,14.05"},{"cmdType":"Move","objectId":"24","transformMatrix":"1,0,0,1,-98.2,14.05"}]},{"num":"143","Command":[{"cmdType":"Move","objectId":"23","transformMatrix":"1,0,0,1,247.3,14.05"},{"cmdType":"Move","objectId":"24","transformMatrix":"1,0,0,1,-99.85,14.05"}]},{"num":"144","Command":[{"cmdType":"Move","objectId":"23","transformMatrix":"1,0,0,1,248.5,14.05"},{"cmdType":"Move","objectId":"24","transformMatrix":"1,0,0,1,-101.05,14.05"}]},{"num":"145","Command":[{"cmdType":"Move","objectId":"23","transformMatrix":"1,0,0,1,249.25,14.05"},{"cmdType":"Move","objectId":"24","transformMatrix":"1,0,0,1,-101.75,14.05"}]},{"num":"146","Command":[{"cmdType":"Move","objectId":"23","transformMatrix":"1,0,0,1,249.5,14.05"},{"cmdType":"Move","objectId":"24","transformMatrix":"1,0,0,1,-102,14.05"}]},{"num":"277","Command":[{"cmdType":"Move","objectId":"23","transformMatrix":"1,0,0,1,248.9,14.05"},{"cmdType":"Move","objectId":"24","transformMatrix":"1,0,0,1,-101.4,14.05"}]},{"num":"278","Command":[{"cmdType":"Move","objectId":"23","transformMatrix":"1,0,0,1,247.95,14.05"},{"cmdType":"Move","objectId":"24","transformMatrix":"1,0,0,1,-100.5,14.05"}]},{"num":"279","Command":[{"cmdType":"Move","objectId":"23","transformMatrix":"1,0,0,1,246.65,14.05"},{"cmdType":"Move","objectId":"24","transformMatrix":"1,0,0,1,-99.25,14.05"}]},{"num":"280","Command":[{"cmdType":"Move","objectId":"23","transformMatrix":"1,0,0,1,245.05,14.05"},{"cmdType":"Move","objectId":"24","transformMatrix":"1,0,0,1,-97.65,14.05"}]},{"num":"281","Command":[{"cmdType":"Move","objectId":"23","transformMatrix":"1,0,0,1,243.05,14.05"},{"cmdType":"Move","objectId":"24","transformMatrix":"1,0,0,1,-95.75,14.05"}]},{"num":"282","Command":[{"cmdType":"Move","objectId":"23","transformMatrix":"1,0,0,1,240.75,14.05"},{"cmdType":"Move","objectId":"24","transformMatrix":"1,0,0,1,-93.5,14.05"}]},{"num":"283","Command":[{"cmdType":"Move","objectId":"23","transformMatrix":"1,0,0,1,238.1,14.05"},{"cmdType":"Move","objectId":"24","transformMatrix":"1,0,0,1,-90.9,14.05"}]},{"num":"284","Command":[{"cmdType":"Move","objectId":"23","transformMatrix":"1,0,0,1,235.05,14.05"},{"cmdType":"Move","objectId":"24","transformMatrix":"1,0,0,1,-88,14.05"}]},{"num":"285","Command":[{"cmdType":"Move","objectId":"23","transformMatrix":"1,0,0,1,231.7,14.05"},{"cmdType":"Move","objectId":"24","transformMatrix":"1,0,0,1,-84.75,14.05"}]},{"num":"286","Command":[{"cmdType":"Move","objectId":"23","transformMatrix":"1,0,0,1,228,14.05"},{"cmdType":"Move","objectId":"24","transformMatrix":"1,0,0,1,-81.15,14.05"}]},{"num":"287","Command":[{"cmdType":"Move","objectId":"23","transformMatrix":"1,0,0,1,223.95,14.05"},{"cmdType":"Move","objectId":"24","transformMatrix":"1,0,0,1,-77.2,14.05"}]},{"num":"288","Command":[{"cmdType":"Move","objectId":"23","transformMatrix":"1,0,0,1,219.6,14.05"},{"cmdType":"Move","objectId":"24","transformMatrix":"1,0,0,1,-72.95,14.05"}]},{"num":"289","Command":[{"cmdType":"Move","objectId":"23","transformMatrix":"1,0,0,1,214.85,14.05"},{"cmdType":"Move","objectId":"24","transformMatrix":"1,0,0,1,-68.35,14.05"}]},{"num":"290","Command":[{"cmdType":"Move","objectId":"23","transformMatrix":"1,0,0,1,209.8,14.05"},{"cmdType":"Move","objectId":"24","transformMatrix":"1,0,0,1,-63.4,14.05"}]},{"num":"291","Command":[{"cmdType":"Move","objectId":"23","transformMatrix":"1,0,0,1,204.35,14.05"},{"cmdType":"Move","objectId":"24","transformMatrix":"1,0,0,1,-58.15,14.05"}]},{"num":"292","Command":[{"cmdType":"Move","objectId":"23","transformMatrix":"1,0,0,1,198.6,14.05"},{"cmdType":"Move","objectId":"24","transformMatrix":"1,0,0,1,-52.55,14.05"}]},{"num":"293","Command":[{"cmdType":"Move","objectId":"23","transformMatrix":"1,0,0,1,192.5,14.05"},{"cmdType":"Move","objectId":"24","transformMatrix":"1,0,0,1,-46.6,14.05"}]},{"num":"294","Command":[{"cmdType":"Move","objectId":"23","transformMatrix":"1,0,0,1,186.05,14.05"},{"cmdType":"Move","objectId":"24","transformMatrix":"1,0,0,1,-40.35,14.05"}]},{"num":"295","Command":[{"cmdType":"Move","objectId":"23","transformMatrix":"1,0,0,1,179.25,14.05"},{"cmdType":"Move","objectId":"24","transformMatrix":"1,0,0,1,-33.75,14.05"}]},{"num":"296","Command":[{"cmdType":"Move","objectId":"23","transformMatrix":"1,0,0,1,172.1,14.05"},{"cmdType":"Move","objectId":"24","transformMatrix":"1,0,0,1,-26.8,14.05"}]},{"num":"297","Command":[{"cmdType":"Move","objectId":"23","transformMatrix":"1,0,0,1,164.6,14.05"},{"cmdType":"Move","objectId":"24","transformMatrix":"1,0,0,1,-19.55,14.05"}]},{"num":"298","Command":[{"cmdType":"Move","objectId":"23","transformMatrix":"1,0,0,1,156.75,14.05"},{"cmdType":"Move","objectId":"24","transformMatrix":"1,0,0,1,-11.95,14.05"}]},{"num":"299","Command":[{"cmdType":"Move","objectId":"23","transformMatrix":"1,0,0,1,148.6,14.05"},{"cmdType":"Move","objectId":"24","transformMatrix":"1,0,0,1,-4,14.05"}]},{"num":"300","Command":[{"cmdType":"Move","objectId":"23","transformMatrix":"1,0,0,1,140.05,14.05"},{"cmdType":"Move","objectId":"24","transformMatrix":"1,0,0,1,4.3,14.05"}]},{"num":"301","Command":[{"cmdType":"Move","objectId":"23","transformMatrix":"1,0,0,1,131.2,14.05"},{"cmdType":"Move","objectId":"24","transformMatrix":"1,0,0,1,12.9,14.05"}]},{"num":"327","Command":[{"cmdType":"Remove","objectId":"27"},{"cmdType":"Place","charid":"72","objectId":"49","placeAfter":"26","transformMatrix":"1,0,0,1,153.5,76.8"},{"cmdType":"UpdateZOrder","objectId":"28","placeAfter":"49"}]}]}]}}