<?xml version="1.0" encoding="UTF-8"?>
<data>
	
	<events>
		<event id="onEnterScrollView">			
			<media id="anim" action="play" />
		</event>
		
		<event id="onExitScrollView">		
			<media id="anim" action="stop" />
		</event>
	</events>
	
	<image id="bg" x="0" y="0" anim="alpha" animtime="0.2" animdelay="0"><![CDATA[lib/animations/mdl851002_menu_2.png]]></image>
	<svganim id="anim" src="lib/animations/mdl851002_menu_2.json" width="745" height="396" x="-4" y="-6" loop="true" autoplay="false" disableTM="true"/>
</data>
